plover_debugging_console/__init__.py
plover_debugging_console-0.2.5.dist-info/LICENSE
plover_debugging_console-0.2.5.dist-info/METADATA
plover_debugging_console-0.2.5.dist-info/WHEEL
plover_debugging_console-0.2.5.dist-info/entry_points.txt
plover_debugging_console-0.2.5.dist-info/top_level.txt
plover_debugging_console-0.2.5.dist-info/zip-safe
plover_debugging_console-0.2.5.dist-info/RECORD
