Metadata-Version: 2.1
Name: plover-debugging-console
Version: 0.2.5
Summary: A IPython debugging console for Plover.
Home-page: https://github.com/user202729/plover-debugging-console
Author: user202729
License: GNU General Public License v3 or later (GPLv3+)
Keywords: plover plover_plugin
Platform: UNKNOWN
Classifier: Environment :: Plugins
Classifier: License :: OSI Approved :: GNU General Public License v3 or later (GPLv3+)
Classifier: Operating System :: OS Independent
Classifier: Programming Language :: Python :: 3
Requires-Dist: plover (>=4.0.0.dev8)
Requires-Dist: background-zmq-ipython (>=1.20200202.222340)
